lazy_ninja/__init__.py
lazy_ninja/base.py
lazy_ninja/builder.py
lazy_ninja/core.py
lazy_ninja/errors.py
lazy_ninja/file_upload.py
lazy_ninja/helpers.py
lazy_ninja/pagination.py
lazy_ninja/registry.py
lazy_ninja/routes.py
lazy_ninja/cli/__init__.py
lazy_ninja/cli/client_generator.py
lazy_ninja/cli/main.py
lazy_ninja/cli/startproject.py
lazy_ninja/handlers/file_handler.py
lazy_ninja/handlers/response.py
lazy_ninja/middleware/__init__.py
lazy_ninja/middleware/error_handling.py
lazy_ninja/middleware/process_put_patch.py
lazy_ninja/router/async_router.py
lazy_ninja/router/base.py
lazy_ninja/router/sync_router.py
lazy_ninja/utils/__init__.py
lazy_ninja/utils/base.py
lazy_ninja/utils/hooks.py
lazy_ninja/utils/legacy.py
lazy_ninja/utils/model.py
lazy_ninja/utils/schema.py
lazy_ninja-0.6.7.dist-info/licenses/LICENSE
lazy_ninja-0.6.7.dist-info/METADATA
lazy_ninja-0.6.7.dist-info/WHEEL
lazy_ninja-0.6.7.dist-info/entry_points.txt
lazy_ninja-0.6.7.dist-info/top_level.txt
lazy_ninja-0.6.7.dist-info/RECORD
