Metadata-Version: 2.4
Name: lazy-ninja
Version: 0.6.7
Summary: Rapidly generate CRUD API endpoints for your Django models with Django Ninja. Includes dynamic schema generation and customizable hooks.
Author: Augusto Domingos
Project-URL: Homepage, https://github.com/AghastyGD/lazy-ninja
Classifier: Development Status :: 3 - Alpha
Classifier: Intended Audience :: Developers
Classifier: License :: OSI Approved :: MIT License
Classifier: Programming Language :: Python :: 3.10
Classifier: Programming Language :: Python :: 3.11
Classifier: Programming Language :: Python :: 3.12
Classifier: Programming Language :: Python :: 3.13
Classifier: Framework :: Django
Classifier: Framework :: Django :: 4.2
Classifier: Framework :: Django :: 5.0
Classifier: Framework :: Django :: 5.1
License-File: LICENSE
Requires-Dist: django>=4.2
Requires-Dist: django-ninja>=0.22
Requires-Dist: pydantic>=2.0
Requires-Dist: inflect>=7.5
Requires-Dist: colorama>=0.4.6
Provides-Extra: standard
Requires-Dist: openapi-generator-cli[jdk4py]>=7.14.0; extra == "standard"
Provides-Extra: no-jdk
Requires-Dist: openapi-generator-cli>=7.14.0; extra == "no-jdk"
Dynamic: license-file
